LICENSE
MANIFEST.in
README.md
pyproject.toml
setup.py
pyPhasesML/DataManipulation.py
pyPhasesML/DataSet.py
pyPhasesML/DataversionManager.py
pyPhasesML/FeatureExtraction.py
pyPhasesML/Model.py
pyPhasesML/ModelAdapter.py
pyPhasesML/ModelManager.py
pyPhasesML/Plugin.py
pyPhasesML/__init__.py
pyPhasesML/config.yaml
pyPhasesML.egg-info/PKG-INFO
pyPhasesML.egg-info/SOURCES.txt
pyPhasesML.egg-info/dependency_links.txt
pyPhasesML.egg-info/requires.txt
pyPhasesML.egg-info/top_level.txt
pyPhasesML/adapter/ModelKerasAdapter.py
pyPhasesML/adapter/ModelTf1Adapter.py
pyPhasesML/adapter/ModelTorchAdapter.py
pyPhasesML/adapter/__init__.py
pyPhasesML/adapter/torch/CSVLogger.py
pyPhasesML/adapter/torch/Callback.py
pyPhasesML/adapter/torch/CheckPoint.py
pyPhasesML/adapter/torch/CyclicLearningrate.py
pyPhasesML/adapter/torch/FindLearningRate.py
pyPhasesML/adapter/torch/LoadOptimizer.py
pyPhasesML/adapter/torch/SystemCheckPoint.py
pyPhasesML/adapter/torch/__init__.py
pyPhasesML/datapipes/BatchMap.py
pyPhasesML/datapipes/DataLoader.py
pyPhasesML/datapipes/DataPipe.py
pyPhasesML/datapipes/DatasetXY.py
pyPhasesML/datapipes/Manipulator.py
pyPhasesML/datapipes/MemoryCache.py
pyPhasesML/datapipes/MultiSourceMap.py
pyPhasesML/datapipes/PreloadPipe.py
pyPhasesML/datapipes/RecordMap.py
pyPhasesML/datapipes/ShuffleMap.py
pyPhasesML/datapipes/TorchMap.py
pyPhasesML/datapipes/__init__.py
pyPhasesML/exporter/MemmapRecordExporter.py
pyPhasesML/exporter/MemmapRecordSegmentsExporter.py
pyPhasesML/exporter/ModelExporter.py
pyPhasesML/exporter/__init__.py
pyPhasesML/scorer/Scorer.py
pyPhasesML/scorer/ScorerTF.py
pyPhasesML/scorer/ScorerTorch.py
pyPhasesML/scorer/__init__.py