Metadata-Version: 2.4
Name: pyPhasesML
Version: 0.18.4
Summary: A Framework for creating a boilerplate template for ai projects that are ready for MLOps
Home-page: https://gitlab.com/tud.ibmt.public/pyphases/pyphasesml/
Author: Franz Ehrlich
Author-email: fehrlichd@gmail.com
Classifier: Programming Language :: Python :: 3
Classifier: License :: OSI Approved :: MIT License
Classifier: Operating System :: OS Independent
Requires-Python: >=3.5
License-File: LICENSE
Requires-Dist: pyPhases
Requires-Dist: typeguard
Dynamic: author
Dynamic: author-email
Dynamic: classifier
Dynamic: description
Dynamic: description-content-type
Dynamic: home-page
Dynamic: license-file
Dynamic: requires-dist
Dynamic: requires-python
Dynamic: summary
